{"chunk_definitions":[{"chunk_id":"cb7nwketvpyv0","chunk_label":"unnamed-chunk-1","document_id":"F721BAA4","expansion_state":0,"options":{"engine":"r","label":"unnamed-chunk-1","message":false,"warning":false},"row":37,"row_count":1,"visible":true},{"chunk_id":"c71cwocx97jxy","chunk_label":"unnamed-chunk-2","document_id":"F721BAA4","expansion_state":0,"options":{"engine":"r","label":"unnamed-chunk-2","message":false},"row":48,"row_count":1,"visible":true},{"chunk_id":"c7nw85ps1hx2g","chunk_label":"unnamed-chunk-4","document_id":"F721BAA4","expansion_state":0,"options":{"engine":"r","label":"unnamed-chunk-3"},"row":64,"row_count":1,"visible":true},{"chunk_id":"c9iezym09olsa","chunk_label":"unnamed-chunk-5","document_id":"F721BAA4","expansion_state":0,"options":{"engine":"r","label":"unnamed-chunk-4"},"row":109,"row_count":1,"visible":true},{"chunk_id":"cbdsou8ul7nlm","chunk_label":"unnamed-chunk-6","document_id":"F721BAA4","expansion_state":0,"options":{"engine":"r","label":"unnamed-chunk-26"},"row":117,"row_count":1,"visible":true},{"chunk_id":"cm3viwckzdrj2","chunk_label":"unnamed-chunk-7","document_id":"F721BAA4","expansion_state":0,"options":{"engine":"r","label":"unnamed-chunk-6"},"row":128,"row_count":1,"visible":true},{"chunk_id":"chdj2ckn71wrd","chunk_label":"unnamed-chunk-8","document_id":"F721BAA4","expansion_state":0,"options":{"engine":"r","label":"unnamed-chunk-7"},"row":139,"row_count":1,"visible":true},{"chunk_id":"cezobofqlz3y5","chunk_label":"unnamed-chunk-9","document_id":"F721BAA4","expansion_state":0,"options":{"engine":"r","label":"unnamed-chunk-8"},"row":152,"row_count":1,"visible":true},{"chunk_id":"cir5imer54xsc","chunk_label":"unnamed-chunk-10","document_id":"F721BAA4","expansion_state":0,"options":{"engine":"r","label":"unnamed-chunk-9"},"row":166,"row_count":1,"visible":true},{"chunk_id":"c89gvt0ciu5dv","chunk_label":"unnamed-chunk-11","document_id":"F721BAA4","expansion_state":0,"options":{"engine":"r","label":"unnamed-chunk-10"},"row":189,"row_count":1,"visible":true},{"chunk_id":"cwb71qopclp01","chunk_label":"unnamed-chunk-12","document_id":"F721BAA4","expansion_state":0,"options":{"engine":"r","label":"unnamed-chunk-11"},"row":213,"row_count":1,"visible":true},{"chunk_id":"cf7fd718p9hyl","chunk_label":"unnamed-chunk-13","document_id":"F721BAA4","expansion_state":0,"options":{"engine":"r","label":"unnamed-chunk-12"},"row":234,"row_count":1,"visible":true},{"chunk_id":"cs0ekw1qm0rjh","chunk_label":"unnamed-chunk-14","document_id":"F721BAA4","expansion_state":0,"options":{"engine":"r","label":"unnamed-chunk-13"},"row":240,"row_count":1,"visible":true},{"chunk_id":"cq8ag749ouz95","chunk_label":"unnamed-chunk-15","document_id":"F721BAA4","expansion_state":0,"options":{"engine":"r","label":"unnamed-chunk-14"},"row":247,"row_count":1,"visible":true},{"chunk_id":"cmg0kxgwz5dxa","chunk_label":"unnamed-chunk-16","document_id":"F721BAA4","expansion_state":0,"options":{"engine":"r","label":"unnamed-chunk-15"},"row":259,"row_count":1,"visible":true},{"chunk_id":"cst6xfcfrg0ne","chunk_label":"unnamed-chunk-17","document_id":"F721BAA4","expansion_state":0,"options":{"engine":"r","label":"unnamed-chunk-16"},"row":301,"row_count":1,"visible":true},{"chunk_id":"c0l8gxii501ba","chunk_label":"unnamed-chunk-18","document_id":"F721BAA4","expansion_state":0,"options":{"engine":"r","label":"unnamed-chunk-17"},"row":317,"row_count":1,"visible":true},{"chunk_id":"c3w3r3th2arkf","chunk_label":"unnamed-chunk-19","document_id":"F721BAA4","expansion_state":0,"options":{"engine":"r","label":"unnamed-chunk-18"},"row":340,"row_count":1,"visible":true},{"chunk_id":"ctkj958jemj0i","chunk_label":"unnamed-chunk-20","document_id":"F721BAA4","expansion_state":0,"options":{"engine":"r","label":"unnamed-chunk-19"},"row":363,"row_count":1,"visible":true}],"chunk_rendered_width":700,"doc_write_time":1511143682}